{
	"name": "Assignment10",
	"properties": {
		"activities": [
			{
				"name": "ForEach1",
				"type": "ForEach",
				"dependsOn": [],
				"userProperties": [],
				"typeProperties": {
					"items": {
						"value": "@createArray('India','China','Russia')",
						"type": "Expression"
					},
					"activities": [
						{
							"name": "Copy data2",
							"type": "Copy",
							"dependsOn": [],
							"policy": {
								"timeout": "0.12:00:00",
								"retry": 0,
								"retryIntervalInSeconds": 30,
								"secureOutput": false,
								"secureInput": false
							},
							"userProperties": [],
							"typeProperties": {
								"source": {
									"type": "RestSource",
									"httpRequestTimeout": "00:01:40",
									"requestInterval": "00.00:00:00.010",
									"requestMethod": "GET",
									"paginationRules": {
										"supportRFC5988": "true"
									}
								},
								"sink": {
									"type": "JsonSink",
									"storeSettings": {
										"type": "AzureBlobFSWriteSettings"
									},
									"formatSettings": {
										"type": "JsonWriteSettings"
									}
								},
								"enableStaging": false
							},
							"inputs": [
								{
									"referenceName": "Rest_DS_Assignment10",
									"type": "DatasetReference",
									"parameters": {
										"Country": {
											"value": "@item()",
											"type": "Expression"
										}
									}
								}
							],
							"outputs": [
								{
									"referenceName": "Assignment10_json",
									"type": "DatasetReference",
									"parameters": {
										"FileFolder": {
											"value": "@item()",
											"type": "Expression"
										},
										"FileName": {
											"value": "@concat(item(),'.json')",
											"type": "Expression"
										}
									}
								}
							]
						}
					]
				}
			}
		],
		"annotations": [],
		"lastPublishTime": "2023-04-09T16:13:27Z"
	},
	"type": "Microsoft.DataFactory/factories/pipelines"
}